Verilog Project EE619A Group 7/Verilog Project EE619A Group 7/jkb.v

module jk(j,k,clk,reset,Q,Q_bar);
input j,k,clk,reset;
output reg Q,Q_bar;

    always@(posedge clk)
          begin
            if({reset})
            {Q,Q_bar}<={1'b0,1'b1};

            else
                begin
                case({j,k})
                2'b00:{Q,Q_bar}<={Q,Q_bar};
                2'b01:{Q,Q_bar}<={1'b0,1'b1};
                2'b10:{Q,Q_bar}<={1'b1,1'b0};
                2'b11:{Q,Q_bar}<={~Q,Q};
                default:begin end
                endcase
         end          
end
endmodule

Verilog Project EE619A Group 7/Verilog Project EE619A Group 7/count.v
`include "jkb.v"
module count(clk,reset,A);

input clk,reset;
output [3:0]A;
wire [3:0]B;
not(B[0],A[0]);
not(B[1],A[1]);
not(B[2],A[2]);
not(B[3],A[3]);


jk u0(1'b1,1'b1,clk,reset,A[0],B[0]);
jk u1(A[0],A[0],clk,reset,A[1],B[1]);
jk u2(A[0]&A[1],A[0]&A[1],clk,reset,A[2],B[2]);
jk u3(A[0]&A[1]&A[2],A[0]&A[1]&A[2],clk,reset,A[3],B[3]);

endmodule

Verilog Project EE619A Group 7/Verilog Project EE619A Group 7/count_tb.v
`timescale 1ns/1ns
`include "count.v"

module count_tb;  
  reg clk;                       
  reg reset;                      
  wire [3:0] A;                
  integer i;
  
  count   dut ( .clk (clk),.reset (reset),.A (A));  
  
    
   
initial begin 
  clk=0;
  forever #5 clk=~clk;
  end 
  
  initial begin 
    $dumpfile("count_tb.vcd");
    $dumpvars;  
    reset = 1;
    #10;
    $display("%b\t%b\t%b\t%b",A[3],A[2],A[1],A[0]);
    reset =0;
    for(i=0;i<=30;i++)
    begin
        #10;
        $display("%b\t%b\t%b\t%b",A[3],A[2],A[1],A[0]);    
    end
    $finish;  
  end  
endmodule

Verilog Project EE619A Group 7/Verilog Project EE619A Group 7/count_tb.vcd
$date
	Thu May 04 17:41:47 2023
$end
$version
	Icarus Verilog
$end
$timescale
	1ns
$end
$scope module count_tb $end
$var wire 4 ! A [3:0] $end
$var reg 1 " clk $end
$var reg 1 # reset $end
$var integer 32 $ i [31:0] $end
$scope module dut $end
$var wire 4 % B [3:0] $end
$var wire 1 " clk $end
$var wire 1 # reset $end
$var wire 4 & A [3:0] $end
$scope module u0 $end
$var wire 1 " clk $end
$var wire 1 ' j $end
$var wire 1 ( k $end
$var wire 1 # reset $end
$var reg 1 ) Q $end
$var reg 1 * Q_bar $end
$upscope $end
$scope module u1 $end
$var wire 1 " clk $end
$var wire 1 + j $end
$var wire 1 , k $end
$var wire 1 # reset $end
$var reg 1 - Q $end
$var reg 1 . Q_bar $end
$upscope $end
$scope module u2 $end
$var wire 1 " clk $end
$var wire 1 / j $end
$var wire 1 0 k $end
$var wire 1 # reset $end
$var reg 1 1 Q $end
$var reg 1 2 Q_bar $end
$upscope $end
$scope module u3 $end
$var wire 1 " clk $end
$var wire 1 3 j $end
$var wire 1 4 k $end
$var wire 1 # reset $end
$var reg 1 5 Q $end
$var reg 1 6 Q_bar $end
$upscope $end
$upscope $end
$upscope $end
$enddefinitions $end
$comment Show the parameter values. $end
$dumpall
$end
#0
$dumpvars
x6
x5
x4
x3
x2
x1
x0
x/
x.
x-
x,
x+
x*
x)
1(
1'
bx &
bx %
bx $
1#
0"
bx !
$end
#5
00
0/
04
03
b1111 %
0,
0+
0)
1*
0-
1.
01
12
b0 !
b0 &
05
16
1"
#10
0"
b0 $
0#
#15
1,
1+
b1 !
b1 &
1)
b1110 %
0*
1"
#20
0"
b1 $
#25
0,
0+
0)
1*
b10 !
b10 &
1-
b1101 %
0.
1"
#30
0"
b10 $
#35
10
1/
1,
1+
b11 !
b11 &
1)
b1100 %
0*
1"
#40
0"
b11 $
#45
00
0/
04
03
0,
0+
0)
1*
0-
1.
b100 !
b100 &
11
b1011 %
02
1"
#50
0"
b100 $
#55
1,
1+
b101 !
b101 &
1)
b1010 %
0*
1"
#60
0"
b101 $
#65
0,
0+
0)
1*
b110 !
b110 &
1-
b1001 %
0.
1"
#70
0"
b110 $
#75
14
13
10
1/
1,
1+
b111 !
b111 &
1)
b1000 %
0*
1"
#80
0"
b111 $
#85
00
0/
04
03
0,
0+
0)
1*
0-
1.
01
12
b1000 !
b1000 &
15
b111 %
06
1"
#90
0"
b1000 $
#95
1,
1+
b1001 !
b1001 &
1)
b110 %
0*
1"
#100
0"
b1001 $
#105
0,
0+
0)
1*
b1010 !
b1010 &
1-
b101 %
0.
1"
#110
0"
b1010 $
#115
10
1/
1,
1+
b1011 !
b1011 &
1)
b100 %
0*
1"
#120
0"
b1011 $
#125
00
0/
04
03
0,
0+
0)
1*
0-
1.
b1100 !
b1100 &
11
b11 %
02
1"
#130
0"
b1100 $
#135
1,
1+
b1101 !
b1101 &
1)
b10 %
0*
1"
#140
0"
b1101 $
#145
0,
0+
0)
1*
b1110 !
b1110 &
1-
b1 %
0.
1"
#150
0"
b1110 $
#155
14
13
10
1/
1,
1+
b1111 !
b1111 &
1)
b0 %
0*
1"
#160
0"
b1111 $
#165
00
0/
04
03
0,
0+
0)
1*
0-
1.
01
12
b0 !
b0 &
05
b1111 %
16
1"
#170
0"
b10000 $
#175
1,
1+
b1 !
b1 &
1)
b1110 %
0*
1"
#180
0"
b10001 $
#185
0,
0+
0)
1*
b10 !
b10 &
1-
b1101 %
0.
1"
#190
0"
b10010 $
#195
10
1/
1,
1+
b11 !
b11 &
1)
b1100 %
0*
1"
#200
0"
b10011 $
#205
00
0/
04
03
0,
0+
0)
1*
0-
1.
b100 !
b100 &
11
b1011 %
02
1"
#210
0"
b10100 $
#215
1,
1+
b101 !
b101 &
1)
b1010 %
0*
1"
#220
0"
b10101 $
#225
0,
0+
0)
1*
b110 !
b110 &
1-
b1001 %
0.
1"
#230
0"
b10110 $
#235
14
13
10
1/
1,
1+
b111 !
b111 &
1)
b1000 %
0*
1"
#240
0"
b10111 $
#245
00
0/
04
03
0,
0+
0)
1*
0-
1.
01
12
b1000 !
b1000 &
15
b111 %
06
1"
#250
0"
b11000 $
#255
1,
1+
b1001 !
b1001 &
1)
b110 %
0*
1"
#260
0"
b11001 $
#265
0,
0+
0)
1*
b1010 !
b1010 &
1-
b101 %
0.
1"
#270
0"
b11010 $
#275
10
1/
1,
1+
b1011 !
b1011 &
1)
b100 %
0*
1"
#280
0"
b11011 $
#285
00
0/
04
03
0,
0+
0)
1*
0-
1.
b1100 !
b1100 &
11
b11 %
02
1"
#290
0"
b11100 $
#295
1,
1+
b1101 !
b1101 &
1)
b10 %
0*
1"
#300
0"
b11101 $
#305
0,
0+
0)
1*
b1110 !
b1110 &
1-
b1 %
0.
1"
#310
0"
b11110 $
#315
14
13
10
1/
1,
1+
b1111 !
b1111 &
1)
b0 %
0*
1"
#320
0"
b11111 $
