Verilog Project EE619A Group 7/Verilog Project EE619A Group 7/jkb.v

module jk(j,k,clk,reset,Q,Q_bar);
input j,k,clk,reset;
output reg Q,Q_bar;

    always@(posedge clk)
          begin
            if({reset})
            {Q,Q_bar}<={1'b0,1'b1};

            else
                begin
                case({j,k})
                2'b00:{Q,Q_bar}<={Q,Q_bar};
                2'b01:{Q,Q_bar}<={1'b0,1'b1};
                2'b10:{Q,Q_bar}<={1'b1,1'b0};
                2'b11:{Q,Q_bar}<={~Q,Q};
                default:begin end
                endcase
         end          
end
endmodule

Verilog Project EE619A Group 7/Verilog Project EE619A Group 7/jkb_tb.v
`timescale 1ns/1ns
`include "jkb.v"
module jkb_tb;
reg clk,reset,j,k;
wire q,qbar;

  jk dut(j,k,clk,reset,q,qbar);
  
  initial begin 
  clk=0;
  forever #5 clk=~clk;
  end
  
  initial 
    begin
    $dumpfile("jkb_tb.vcd");
    $dumpvars;
     reset=1;
     #10;
    $display("j=%b\tk=%b\tq=%b\tqbar=%b",j,k,q,qbar);
     reset=0;
     #10;
$display("j=%b\tk=%b\tq=%b\tqbar=%b",j,k,q,qbar);
     j = 1'b0;
     k = 1'b0;     
     #10;
    $display("j=%b\tk=%b\tq=%b\tqbar=%b",j,k,q,qbar);
     j = 1'b0;
     k = 1'b1;     
     #10;
     $display("j=%b\tk=%b\tq=%b\tqbar=%b",j,k,q,qbar);
     j = 1'b1;
     k = 1'b0;     
     #10;
     $display("j=%b\tk=%b\tq=%b\tqbar=%b",j,k,q,qbar);
     j = 1'b1;
     k = 1'b1;
     #10;
  $display("j=%b\tk=%b\tq=%b\tqbar=%b",j,k,q,qbar);
     $finish;
    end 
endmodule

Verilog Project EE619A Group 7/Verilog Project EE619A Group 7/jkb_tb.vcd
$date
	Thu May 04 16:58:31 2023
$end
$version
	Icarus Verilog
$end
$timescale
	1ns
$end
$scope module jkb_tb $end
$var wire 1 ! qbar $end
$var wire 1 " q $end
$var reg 1 # clk $end
$var reg 1 $ j $end
$var reg 1 % k $end
$var reg 1 & reset $end
$scope module dut $end
$var wire 1 # clk $end
$var wire 1 $ j $end
$var wire 1 % k $end
$var wire 1 & reset $end
$var reg 1 " Q $end
$var reg 1 ! Q_bar $end
$upscope $end
$upscope $end
$enddefinitions $end
$comment Show the parameter values. $end
$dumpall
$end
#0
$dumpvars
1&
x%
x$
0#
x"
x!
$end
#5
0"
1!
1#
#10
0#
0&
#15
1#
#20
0#
0%
0$
#25
1#
#30
0#
1%
#35
1#
#40
0#
0%
1$
#45
1"
0!
1#
#50
0#
1%
#55
0"
1!
1#
